README.rst
decide_host/__init__.py
decide_host/admin.py
decide_host/apps.py
decide_host/models.py
decide_host/serializers.py
decide_host/urls.py
decide_host/views.py
decide_host/management/commands/import_trials.py
decide_host/management/commands/merge_subjects.py
decide_host/migrations/0001_initial.py
decide_host/migrations/0002_alter_component_options_alter_controller_options_and_more.py
decide_host/migrations/__init__.py
django_decide_host-0.3.11.dist-info/METADATA
django_decide_host-0.3.11.dist-info/WHEEL
django_decide_host-0.3.11.dist-info/RECORD
