Metadata-Version: 2.4
Name: django-decide-host
Version: 0.3.11
Summary: A Django-based database for trials and events in the decide operant control system
Project-URL: Homepage, https://github.com/melizalab/django-decide-host
Author-email: C Daniel Meliza <dan@meliza.org>
Maintainer-email: C Daniel Meliza <dan@meliza.org>
License: BSD 3-Clause License
Classifier: Development Status :: 4 - Beta
Classifier: Framework :: Django
Classifier: Intended Audience :: Science/Research
Classifier: License :: OSI Approved :: BSD License
Classifier: Programming Language :: Python
Classifier: Programming Language :: Python :: 3.10
Classifier: Programming Language :: Python :: 3.11
Classifier: Programming Language :: Python :: 3.12
Classifier: Topic :: Internet :: WWW/HTTP
Classifier: Topic :: Internet :: WWW/HTTP :: Dynamic Content
Classifier: Topic :: Scientific/Engineering
Requires-Python: >=3.10
Requires-Dist: django-filter>=22.1
Requires-Dist: djangorestframework
Requires-Dist: djangorestframework-link-header-pagination
Requires-Dist: django~=5.2
